ethereum/__init__.py
ledger_app_clients.ethereum-2.2.3.dist-info/LICENCE.txt
ledger_app_clients.ethereum-2.2.3.dist-info/METADATA
ledger_app_clients.ethereum-2.2.3.dist-info/WHEEL
ledger_app_clients.ethereum-2.2.3.dist-info/top_level.txt
ledger_app_clients.ethereum-2.2.3.dist-info/RECORD
